{"dependencies":[{"kind":"library","id":"chrome.src.common_exp","children":[{"superclass":{"name":"Object","refId":"dart.core/Object"},"isAbstract":true,"interfaces":[{"name":"Serializable","refId":"dart.js/Serializable","arguments":[{"name":"String","refId":"dart.core/String"}]}],"kind":"class","name":"ChromeEnum","id":"ChromeEnum","comment":"\nThe abstract superclass of Chrome enums.\n","children":[{"returnType":{"name":"String","refId":"dart.core/String"},"kind":"method","name":"toJs","id":"toJs0()","line":"37"},{"returnType":{"name":"String","refId":"dart.core/String"},"kind":"method","name":"toString","id":"toString0()","line":"38"},{"ref":{"name":"String","refId":"dart.core/String"},"isFinal":true,"kind":"variable","name":"value","id":"value","line":"33"},{"kind":"constructor","name":"","id":"1()","children":[{"ref":{"name":"String","refId":"dart.core/String"},"initializedField":{"name":"value","refId":"chrome.src.common_exp/ChromeEnum/value"},"kind":"param","name":"value","id":"value"}],"line":"35"}],"line":"32"},{"superclass":{"name":"Object","refId":"dart.core/Object"},"isAbstract":true,"interfaces":[{"name":"Serializable","refId":"dart.js/Serializable","arguments":[{"name":"JsObject","refId":"dart.js/JsObject"}]}],"kind":"class","name":"ChromeObject","id":"ChromeObject","comment":"\nThe abstract superclass of objects that can hold [JsObject] proxies.\n","children":[{"returnType":{"name":"JsObject","refId":"dart.js/JsObject"},"kind":"method","name":"toJs","id":"toJs0()","line":"24"},{"returnType":{"name":"String","refId":"dart.core/String"},"kind":"method","name":"toString","id":"toString0()","line":"26"},{"ref":{"name":"JsObject","refId":"dart.js/JsObject"},"isFinal":true,"kind":"variable","name":"proxy","id":"proxy","line":"10"},{"kind":"constructor","name":"","id":"0()","comment":"\nCreate a new instance of a `ChromeObject`, which creates and delegates to\na JsObject proxy.\n","line":"16"},{"kind":"constructor","name":"fromProxy","id":"fromProxy1()","comment":"\nCreate a new instance of a `ChromeObject`, which delegates to the given\nJsObject proxy.\n","children":[{"ref":{"name":"JsObject","refId":"dart.js/JsObject"},"initializedField":{"name":"proxy","refId":"chrome.src.common_exp/ChromeObject/proxy"},"kind":"param","name":"proxy","id":"proxy"}],"line":"22"}],"line":"9"}],"uri":"file:///home/ubuntu/src/github.com/dart-gde/chrome_gen.dart/lib/src/common_exp.dart","line":"2"},{"kind":"library","name":"dart:js","id":"dart.js","children":[{"superclass":{"name":"Object","refId":"dart.core/Object"},"isAbstract":true,"kind":"class","name":"Serializable","id":"Serializable","children":[{"returnType":{"name":"T","refId":"dart.js/Serializable/T"},"kind":"method","name":"toJs","id":"toJs0()","line":"168"},{"kind":"typeparam","name":"T","id":"T"}],"line":"167"}],"uri":"dart-sdk/lib/js/dart2js/js_dart2js.dart","line":"5"},{"kind":"library","name":"dart:core","id":"dart.core","comment":"\n\nBuilt-in types, collections,\nand other core functionality for every Dart program.\n\nThis library is automatically imported.\n\nSome classes in this library,\nsuch as [String] and [num],\nsupport Dart's built-in data types.\nOther classes, such as [List] and [Map], provide data structures\nfor managing collections of objects.\nAnd still other classes represent commonly used types of data\nsuch as URIs, dates and times, and errors.\n\n## Numbers and booleans\n\n[int] and [double] provide support for Dart's built-in numerical data types:\nintegers and double-precision floating point numbers, respectively.\nAn object of type [bool] is either true or false.\nVariables of these types can be constructed from literals:\n\n    int meaningOfLife = 42;\n    double valueOfPi  = 3.141592;\n    bool visible      = true;\n\n## Strings and regular expressions\n\nA [String] is immutable and represents a sequence of characters.\n\n    String shakespeareQuote = \"All the world's a stage, ...\";\n\n[StringBuffer] provides a way to construct strings efficiently.\n\n    StringBuffer moreShakespeare = new StringBuffer();\n    moreShakespeare.write('And all the men and women ');\n    moreShakespeare.write('merely players; ...');\n\nThe String and StringBuffer classes implement string concatenation,\ninterpolation, and other string manipulation features.\n\n    String philosophy = 'Live on ';\n    String get palindrome => philosophy + philosophy.split('').reversed.join();\n\n[RegExp] implements Dart regular expressions,\nwhich provide a grammar for matching patterns within text.\nFor example, here's a regular expression that matches\na string of one or more digits:\n\n    var numbers = new RegExp(r'\\d+');\n\nDart regular expressions have the same syntax and semantics as\nJavaScript regular expressions. See\n<http://ecma-international.org/ecma-262/5.1/#sec-15.10>\nfor the specification of JavaScript regular expressions.\n\n## Collections\n\nThe dart:core library provides basic collections,\nsuch as [List], [Map], and [Set].\n\nA List is an ordered collection of objects, with a length.\nLists are sometimes called arrays.\nUse a List when you need to access objects by index.\n\n    List superheroes = [ 'Batman', 'Superman', 'Harry Potter' ];\n\nA Set is an unordered collection of unique objects.\nYou cannot get an item by index (position).\nAdding a duplicate item has no effect.\n\n    Set villians = new Set();\n    villians.add('Joker');\n    villians.addAll( ['Lex Luther', 'Voldemort'] );\n\nA Map is an unordered collection of key-value pairs.\nMaps are sometimes called associative arrays because\nmaps associate a key to some value for easy retrieval.\nKeys are unique.\nUse a Map when you need to access objects\nby a unique identifier.\n\n    Map sidekicks = { 'Batman': 'Robin',\n                      'Superman': 'Lois Lane',\n                      'Harry Potter': 'Ron and Hermione' };\n\nIn addition to these classes,\ndart:core contains [Iterable],\nan interface that defines functionality\ncommon in collections of objects.\nExamples include the ability\nto run a function on each element in the collection,\nto apply a test to each element, \nto retrieve an object, and to determine length.\n\nIterable is implemented by List and Set,\nand used by Map for its keys and values.\n\nFor other kinds of collections, check out the\n[dart:collection](#dart-collection) library.\n\n## Date and time\n\nUse [DateTime] to represent a point in time\nand [Duration] to represent a span of time.\n\nYou can create DateTime objects with constructors\nor by parsing a correctly formatted string.\n\n    DateTime now = new DateTime.now();\n    DateTime berlinWallFell = new DateTime(1989, 11, 9);\n    DateTime moonLanding = DateTime.parse(\"1969-07-20\");\n\nCreate a Duration object specifying the individual time units.\n\n    Duration timeRemaining = new Duration(hours:56, minutes:14);\n\nIn addition to DateTime and Duration,\ndart:core contains the [Stopwatch] class for measuring elapsed time.\n    \n## Uri\n\nA [Uri] object represents a uniform resource identifier,\nwhich identifies a resource on the web.\n\n    Uri dartlang = Uri.parse('http://dartlang.org/');\n    \n## Errors\n\nThe [Error] class represents the occurrence of an error\nduring runtime.\nSubclasses of this class represent specific kinds of errors.\n\n## Other documentation\n\nFor more information about how to use the built-in types, refer to\n[Built-in Types](http://www.dartlang.org/docs/dart-up-and-running/contents/ch02.html#built-in-types)\nin Chapter 2 of\n[Dart: Up and Running](http://www.dartlang.org/docs/dart-up-and-running/).\n\nAlso, see\n[dart:core - Numbers, Collections, Strings, and More](http://www.dartlang.org/docs/dart-up-and-running/contents/ch03.html#ch03-dartcore---strings-collections-and-more)\nfor more coverage of classes in this package.\n\nThe \n[Dart Language Specification](http://www.dartlang.org/docs/spec/)\nprovides technical details.\n","children":[{"kind":"class","name":"Object","id":"Object","comment":"\nThe base class for all Dart objects.\n\nBecause Object is the root of the Dart class hierarchy,\nevery other Dart class is a subclass of Object.\n\nWhen you define a class, you should override [toString]\nto return a string describing an instance of that class.\nYou might also need to define [hashCode] and [==], as described in the\n[Implementing map keys]\n(http://www.dartlang.org/docs/dart-up-and-running/contents/ch03.html#ch03-implementing-map-keys)\nsection of the [library tour]\n(http://www.dartlang.org/docs/dart-up-and-running/contents/ch03.html).\n","children":[{"returnType":{"name":"bool","refId":"dart.core/bool"},"isOperator":true,"kind":"method","name":"==","id":"==1()","comment":"\nThe equality operator.\n\nThe default behavior for all [Object]s is to return true if and\nonly if [:this:] and [other] are the same object.\n\nOverride this method to specify a different equality relation on\na class. The overriding method must still be an equivalence relation.\nThat is, it must be:\n\n * Total: It must return a boolean for all arguments. It should never throw\n   or return `null`.\n\n * Reflexive: For all objects `o`, `o == o` must be true.\n\n * Symmetric: For all objects `o1` and `o2`, `o1 == o2` and `o2 == o1` must\n   either both be true, or both be false.\n\n * Transitive: For all objects `o1`, `o2`, and `o3`, if `o1 == o2` and\n   `o2 == o3` are true, then `o1 == o3` must be true.\n\nThe method should also be consistent over time, so equality of two objects\nshould not change over time, or at least only change if one of the objects\nwas modified.\n\nIf a subclass overrides the equality operator it should override\nthe [hashCode] method as well to maintain consistency.\n","children":[{"kind":"param","name":"other","id":"other"}],"line":"59"},{"returnType":{"name":"String","refId":"dart.core/String"},"kind":"method","name":"toString","id":"toString0()","comment":"\nReturns a string representation of this object.\n","line":"78"},{"kind":"method","name":"noSuchMethod","id":"noSuchMethod1()","comment":"\n[noSuchMethod] is invoked when users invoke a non-existant method\non an object. The name of the method and the arguments of the\ninvocation are passed to [noSuchMethod] in an [Invocation].\nIf [noSuchMethod] returns a value, that value becomes the result of\nthe original invocation.\n\nThe default behavior of [noSuchMethod] is to throw a\n[noSuchMethodError].\n","children":[{"ref":{"name":"Invocation","refId":"dart.core/Invocation"},"kind":"param","name":"invocation","id":"invocation"}],"line":"90"},{"ref":{"name":"int","refId":"dart.core/int"},"kind":"property","name":"hashCode","id":"hashCode","comment":"\nGet a hash code for this object.\n\nAll objects have hash codes. Hash codes are guaranteed to be the\nsame for objects that are equal when compared using the equality\noperator [:==:]. Other than that there are no guarantees about\nthe hash codes. They will not be consistent between runs and\nthere are no distribution guarantees.\n\nIf a subclass overrides [hashCode] it should override the\nequality operator as well to maintain consistency.\n","line":"73"},{"ref":{"name":"Type","refId":"dart.core/Type"},"kind":"property","name":"runtimeType","id":"runtimeType","comment":"\nA representation of the runtime type of the object.\n","line":"95"},{"kind":"constructor","name":"","id":"0()","comment":"\nCreates a new [Object] instance.\n\n[Object] instances have no meaningful state, and are only useful\nthrough their identity. An [Object] instance is equal to itself\nonly.\n","line":"29"}],"uri":"dart-sdk/lib/core/object.dart","line":"21"}],"uri":"dart-sdk/lib/core/core.dart","line":"153"}],"kind":"library","id":"chrome.downloads","children":[{"returnType":{"name":"SuggestFilenameCallback","refId":"chrome.src.common_exp/SuggestFilenameCallback"},"kind":"method","name":"_createSuggestFilenameCallback","id":"_createSuggestFilenameCallback1()","children":[{"ref":{"name":"JsObject","refId":"dart.js/JsObject"},"kind":"param","name":"proxy","id":"proxy"}],"isPrivate":true,"line":"592"},{"returnType":{"name":"LongDelta","refId":"chrome.downloads/LongDelta"},"kind":"method","name":"_createLongDelta","id":"_createLongDelta1()","children":[{"ref":{"name":"JsObject","refId":"dart.js/JsObject"},"kind":"param","name":"proxy","id":"proxy"}],"isPrivate":true,"line":"591"},{"returnType":{"name":"BooleanDelta","refId":"chrome.downloads/BooleanDelta"},"kind":"method","name":"_createBooleanDelta","id":"_createBooleanDelta1()","children":[{"ref":{"name":"JsObject","refId":"dart.js/JsObject"},"kind":"param","name":"proxy","id":"proxy"}],"isPrivate":true,"line":"590"},{"returnType":{"name":"StringDelta","refId":"chrome.downloads/StringDelta"},"kind":"method","name":"_createStringDelta","id":"_createStringDelta1()","children":[{"ref":{"name":"JsObject","refId":"dart.js/JsObject"},"kind":"param","name":"proxy","id":"proxy"}],"isPrivate":true,"line":"589"},{"returnType":{"name":"InterruptReason","refId":"chrome.downloads/InterruptReason"},"kind":"method","name":"_createInterruptReason","id":"_createInterruptReason1()","children":[{"ref":{"name":"String","refId":"dart.core/String"},"kind":"param","name":"value","id":"value"}],"isPrivate":true,"line":"588"},{"returnType":{"name":"State","refId":"chrome.downloads/State"},"kind":"method","name":"_createState","id":"_createState1()","children":[{"ref":{"name":"String","refId":"dart.core/String"},"kind":"param","name":"value","id":"value"}],"isPrivate":true,"line":"587"},{"returnType":{"name":"DangerType","refId":"chrome.downloads/DangerType"},"kind":"method","name":"_createDangerType","id":"_createDangerType1()","children":[{"ref":{"name":"String","refId":"dart.core/String"},"kind":"param","name":"value","id":"value"}],"isPrivate":true,"line":"586"},{"returnType":{"name":"HeaderNameValuePair","refId":"chrome.downloads/HeaderNameValuePair"},"kind":"method","name":"_createHeaderNameValuePair","id":"_createHeaderNameValuePair1()","children":[{"ref":{"name":"JsObject","refId":"dart.js/JsObject"},"kind":"param","name":"proxy","id":"proxy"}],"isPrivate":true,"line":"585"},{"returnType":{"name":"HttpMethod","refId":"chrome.downloads/HttpMethod"},"kind":"method","name":"_createHttpMethod","id":"_createHttpMethod1()","children":[{"ref":{"name":"String","refId":"dart.core/String"},"kind":"param","name":"value","id":"value"}],"isPrivate":true,"line":"584"},{"returnType":{"name":"FilenameConflictAction","refId":"chrome.downloads/FilenameConflictAction"},"kind":"method","name":"_createFilenameConflictAction","id":"_createFilenameConflictAction1()","children":[{"ref":{"name":"String","refId":"dart.core/String"},"kind":"param","name":"value","id":"value"}],"isPrivate":true,"line":"583"},{"returnType":{"name":"OnDeterminingFilenameEvent","refId":"chrome.downloads/OnDeterminingFilenameEvent"},"kind":"method","name":"_createOnDeterminingFilenameEvent","id":"_createOnDeterminingFilenameEvent2()","children":[{"ref":{"name":"JsObject","refId":"dart.js/JsObject"},"kind":"param","name":"downloadItem","id":"downloadItem"},{"ref":{"name":"JsObject","refId":"dart.js/JsObject"},"kind":"param","name":"suggest","id":"suggest"}],"isPrivate":true,"line":"581"},{"returnType":{"name":"DownloadDelta","refId":"chrome.downloads/DownloadDelta"},"kind":"method","name":"_createDownloadDelta","id":"_createDownloadDelta1()","children":[{"ref":{"name":"JsObject","refId":"dart.js/JsObject"},"kind":"param","name":"proxy","id":"proxy"}],"isPrivate":true,"line":"580"},{"returnType":{"name":"DownloadItem","refId":"chrome.downloads/DownloadItem"},"kind":"method","name":"_createDownloadItem","id":"_createDownloadItem1()","children":[{"ref":{"name":"JsObject","refId":"dart.js/JsObject"},"kind":"param","name":"proxy","id":"proxy"}],"isPrivate":true,"line":"579"},{"ref":{"name":"ChromeDownloads","refId":"chrome.downloads/ChromeDownloads"},"isFinal":true,"kind":"variable","name":"downloads","id":"downloads","comment":"Accessor for the `chrome.downloads` namespace.","line":"8"},{"superclass":{"name":"ChromeObject","refId":"chrome.src.common_exp/ChromeObject"},"kind":"class","name":"GetFileIconOptions","id":"GetFileIconOptions","children":[{"isSetter":true,"kind":"method","name":"size=","id":"size=1()","children":[{"ref":{"name":"int","refId":"dart.core/int"},"kind":"param","name":"value","id":"value"}],"line":"576"},{"ref":{"name":"int","refId":"dart.core/int"},"kind":"property","name":"size","id":"size","line":"575"},{"kind":"constructor","name":"","id":"1()","children":[{"ref":{"name":"int","refId":"dart.core/int"},"isOptional":true,"isNamed":true,"kind":"param","name":"size","id":"size"}],"line":"569"},{"kind":"constructor","name":"fromProxy","id":"fromProxy1()","children":[{"ref":{"name":"JsObject","refId":"dart.js/JsObject"},"kind":"param","name":"proxy","id":"proxy"}],"line":"573"}],"line":"567"},{"superclass":{"name":"ChromeObject","refId":"chrome.src.common_exp/ChromeObject"},"kind":"class","name":"DownloadDelta","id":"DownloadDelta","children":[{"isSetter":true,"kind":"method","name":"id=","id":"id=1()","children":[{"ref":{"name":"int","refId":"dart.core/int"},"kind":"param","name":"value","id":"value"}],"line":"525"},{"isSetter":true,"kind":"method","name":"url=","id":"url=1()","children":[{"ref":{"name":"StringDelta","refId":"chrome.downloads/StringDelta"},"kind":"param","name":"value","id":"value"}],"line":"528"},{"isSetter":true,"kind":"method","name":"filename=","id":"filename=1()","children":[{"ref":{"name":"StringDelta","refId":"chrome.downloads/StringDelta"},"kind":"param","name":"value","id":"value"}],"line":"531"},{"isSetter":true,"kind":"method","name":"danger=","id":"danger=1()","children":[{"ref":{"name":"StringDelta","refId":"chrome.downloads/StringDelta"},"kind":"param","name":"value","id":"value"}],"line":"534"},{"isSetter":true,"kind":"method","name":"mime=","id":"mime=1()","children":[{"ref":{"name":"StringDelta","refId":"chrome.downloads/StringDelta"},"kind":"param","name":"value","id":"value"}],"line":"537"},{"isSetter":true,"kind":"method","name":"startTime=","id":"startTime=1()","children":[{"ref":{"name":"StringDelta","refId":"chrome.downloads/StringDelta"},"kind":"param","name":"value","id":"value"}],"line":"540"},{"isSetter":true,"kind":"method","name":"endTime=","id":"endTime=1()","children":[{"ref":{"name":"StringDelta","refId":"chrome.downloads/StringDelta"},"kind":"param","name":"value","id":"value"}],"line":"543"},{"isSetter":true,"kind":"method","name":"state=","id":"state=1()","children":[{"ref":{"name":"StringDelta","refId":"chrome.downloads/StringDelta"},"kind":"param","name":"value","id":"value"}],"line":"546"},{"isSetter":true,"kind":"method","name":"canResume=","id":"canResume=1()","children":[{"ref":{"name":"BooleanDelta","refId":"chrome.downloads/BooleanDelta"},"kind":"param","name":"value","id":"value"}],"line":"549"},{"isSetter":true,"kind":"method","name":"paused=","id":"paused=1()","children":[{"ref":{"name":"BooleanDelta","refId":"chrome.downloads/BooleanDelta"},"kind":"param","name":"value","id":"value"}],"line":"552"},{"isSetter":true,"kind":"method","name":"error=","id":"error=1()","children":[{"ref":{"name":"StringDelta","refId":"chrome.downloads/StringDelta"},"kind":"param","name":"value","id":"value"}],"line":"555"},{"isSetter":true,"kind":"method","name":"totalBytes=","id":"totalBytes=1()","children":[{"ref":{"name":"LongDelta","refId":"chrome.downloads/LongDelta"},"kind":"param","name":"value","id":"value"}],"line":"558"},{"isSetter":true,"kind":"method","name":"fileSize=","id":"fileSize=1()","children":[{"ref":{"name":"LongDelta","refId":"chrome.downloads/LongDelta"},"kind":"param","name":"value","id":"value"}],"line":"561"},{"isSetter":true,"kind":"method","name":"exists=","id":"exists=1()","children":[{"ref":{"name":"BooleanDelta","refId":"chrome.downloads/BooleanDelta"},"kind":"param","name":"value","id":"value"}],"line":"564"},{"ref":{"name":"int","refId":"dart.core/int"},"kind":"property","name":"id","id":"id","line":"524"},{"ref":{"name":"StringDelta","refId":"chrome.downloads/StringDelta"},"kind":"property","name":"url","id":"url","line":"527"},{"ref":{"name":"StringDelta","refId":"chrome.downloads/StringDelta"},"kind":"property","name":"filename","id":"filename","line":"530"},{"ref":{"name":"StringDelta","refId":"chrome.downloads/StringDelta"},"kind":"property","name":"danger","id":"danger","line":"533"},{"ref":{"name":"StringDelta","refId":"chrome.downloads/StringDelta"},"kind":"property","name":"mime","id":"mime","line":"536"},{"ref":{"name":"StringDelta","refId":"chrome.downloads/StringDelta"},"kind":"property","name":"startTime","id":"startTime","line":"539"},{"ref":{"name":"StringDelta","refId":"chrome.downloads/StringDelta"},"kind":"property","name":"endTime","id":"endTime","line":"542"},{"ref":{"name":"StringDelta","refId":"chrome.downloads/StringDelta"},"kind":"property","name":"state","id":"state","line":"545"},{"ref":{"name":"BooleanDelta","refId":"chrome.downloads/BooleanDelta"},"kind":"property","name":"canResume","id":"canResume","line":"548"},{"ref":{"name":"BooleanDelta","refId":"chrome.downloads/BooleanDelta"},"kind":"property","name":"paused","id":"paused","line":"551"},{"ref":{"name":"StringDelta","refId":"chrome.downloads/StringDelta"},"kind":"property","name":"error","id":"error","line":"554"},{"ref":{"name":"LongDelta","refId":"chrome.downloads/LongDelta"},"kind":"property","name":"totalBytes","id":"totalBytes","line":"557"},{"ref":{"name":"LongDelta","refId":"chrome.downloads/LongDelta"},"kind":"property","name":"fileSize","id":"fileSize","line":"560"},{"ref":{"name":"BooleanDelta","refId":"chrome.downloads/BooleanDelta"},"kind":"property","name":"exists","id":"exists","line":"563"},{"kind":"constructor","name":"","id":"14()","children":[{"ref":{"name":"int","refId":"dart.core/int"},"isOptional":true,"isNamed":true,"kind":"param","name":"id","id":"id"},{"ref":{"name":"StringDelta","refId":"chrome.downloads/StringDelta"},"isOptional":true,"isNamed":true,"kind":"param","name":"url","id":"url"},{"ref":{"name":"StringDelta","refId":"chrome.downloads/StringDelta"},"isOptional":true,"isNamed":true,"kind":"param","name":"filename","id":"filename"},{"ref":{"name":"StringDelta","refId":"chrome.downloads/StringDelta"},"isOptional":true,"isNamed":true,"kind":"param","name":"danger","id":"danger"},{"ref":{"name":"StringDelta","refId":"chrome.downloads/StringDelta"},"isOptional":true,"isNamed":true,"kind":"param","name":"mime","id":"mime"},{"ref":{"name":"StringDelta","refId":"chrome.downloads/StringDelta"},"isOptional":true,"isNamed":true,"kind":"param","name":"startTime","id":"startTime"},{"ref":{"name":"StringDelta","refId":"chrome.downloads/StringDelta"},"isOptional":true,"isNamed":true,"kind":"param","name":"endTime","id":"endTime"},{"ref":{"name":"StringDelta","refId":"chrome.downloads/StringDelta"},"isOptional":true,"isNamed":true,"kind":"param","name":"state","id":"state"},{"ref":{"name":"BooleanDelta","refId":"chrome.downloads/BooleanDelta"},"isOptional":true,"isNamed":true,"kind":"param","name":"canResume","id":"canResume"},{"ref":{"name":"BooleanDelta","refId":"chrome.downloads/BooleanDelta"},"isOptional":true,"isNamed":true,"kind":"param","name":"paused","id":"paused"},{"ref":{"name":"StringDelta","refId":"chrome.downloads/StringDelta"},"isOptional":true,"isNamed":true,"kind":"param","name":"error","id":"error"},{"ref":{"name":"LongDelta","refId":"chrome.downloads/LongDelta"},"isOptional":true,"isNamed":true,"kind":"param","name":"totalBytes","id":"totalBytes"},{"ref":{"name":"LongDelta","refId":"chrome.downloads/LongDelta"},"isOptional":true,"isNamed":true,"kind":"param","name":"fileSize","id":"fileSize"},{"ref":{"name":"BooleanDelta","refId":"chrome.downloads/BooleanDelta"},"isOptional":true,"isNamed":true,"kind":"param","name":"exists","id":"exists"}],"line":"505"},{"kind":"constructor","name":"fromProxy","id":"fromProxy1()","children":[{"ref":{"name":"JsObject","refId":"dart.js/JsObject"},"kind":"param","name":"proxy","id":"proxy"}],"line":"522"}],"line":"503"},{"superclass":{"name":"ChromeObject","refId":"chrome.src.common_exp/ChromeObject"},"kind":"class","name":"BooleanDelta","id":"BooleanDelta","children":[{"isSetter":true,"kind":"method","name":"previous=","id":"previous=1()","children":[{"ref":{"name":"bool","refId":"dart.core/bool"},"kind":"param","name":"value","id":"value"}],"line":"497"},{"isSetter":true,"kind":"method","name":"current=","id":"current=1()","children":[{"ref":{"name":"bool","refId":"dart.core/bool"},"kind":"param","name":"value","id":"value"}],"line":"500"},{"ref":{"name":"bool","refId":"dart.core/bool"},"kind":"property","name":"previous","id":"previous","line":"496"},{"ref":{"name":"bool","refId":"dart.core/bool"},"kind":"property","name":"current","id":"current","line":"499"},{"kind":"constructor","name":"","id":"2()","children":[{"ref":{"name":"bool","refId":"dart.core/bool"},"isOptional":true,"isNamed":true,"kind":"param","name":"previous","id":"previous"},{"ref":{"name":"bool","refId":"dart.core/bool"},"isOptional":true,"isNamed":true,"kind":"param","name":"current","id":"current"}],"line":"489"},{"kind":"constructor","name":"fromProxy","id":"fromProxy1()","children":[{"ref":{"name":"JsObject","refId":"dart.js/JsObject"},"kind":"param","name":"proxy","id":"proxy"}],"line":"494"}],"line":"487"},{"superclass":{"name":"ChromeObject","refId":"chrome.src.common_exp/ChromeObject"},"kind":"class","name":"LongDelta","id":"LongDelta","children":[{"isSetter":true,"kind":"method","name":"previous=","id":"previous=1()","children":[{"ref":{"name":"int","refId":"dart.core/int"},"kind":"param","name":"value","id":"value"}],"line":"481"},{"isSetter":true,"kind":"method","name":"current=","id":"current=1()","children":[{"ref":{"name":"int","refId":"dart.core/int"},"kind":"param","name":"value","id":"value"}],"line":"484"},{"ref":{"name":"int","refId":"dart.core/int"},"kind":"property","name":"previous","id":"previous","line":"480"},{"ref":{"name":"int","refId":"dart.core/int"},"kind":"property","name":"current","id":"current","line":"483"},{"kind":"constructor","name":"","id":"2()","children":[{"ref":{"name":"int","refId":"dart.core/int"},"isOptional":true,"isNamed":true,"kind":"param","name":"previous","id":"previous"},{"ref":{"name":"int","refId":"dart.core/int"},"isOptional":true,"isNamed":true,"kind":"param","name":"current","id":"current"}],"line":"473"},{"kind":"constructor","name":"fromProxy","id":"fromProxy1()","children":[{"ref":{"name":"JsObject","refId":"dart.js/JsObject"},"kind":"param","name":"proxy","id":"proxy"}],"line":"478"}],"line":"471"},{"superclass":{"name":"ChromeObject","refId":"chrome.src.common_exp/ChromeObject"},"kind":"class","name":"StringDelta","id":"StringDelta","children":[{"isSetter":true,"kind":"method","name":"previous=","id":"previous=1()","children":[{"ref":{"name":"String","refId":"dart.core/String"},"kind":"param","name":"value","id":"value"}],"line":"465"},{"isSetter":true,"kind":"method","name":"current=","id":"current=1()","children":[{"ref":{"name":"String","refId":"dart.core/String"},"kind":"param","name":"value","id":"value"}],"line":"468"},{"ref":{"name":"String","refId":"dart.core/String"},"kind":"property","name":"previous","id":"previous","line":"464"},{"ref":{"name":"String","refId":"dart.core/String"},"kind":"property","name":"current","id":"current","line":"467"},{"kind":"constructor","name":"","id":"2()","children":[{"ref":{"name":"String","refId":"dart.core/String"},"isOptional":true,"isNamed":true,"kind":"param","name":"previous","id":"previous"},{"ref":{"name":"String","refId":"dart.core/String"},"isOptional":true,"isNamed":true,"kind":"param","name":"current","id":"current"}],"line":"457"},{"kind":"constructor","name":"fromProxy","id":"fromProxy1()","children":[{"ref":{"name":"JsObject","refId":"dart.js/JsObject"},"kind":"param","name":"proxy","id":"proxy"}],"line":"462"}],"line":"455"},{"superclass":{"name":"ChromeObject","refId":"chrome.src.common_exp/ChromeObject"},"kind":"class","name":"DownloadQuery","id":"DownloadQuery","children":[{"isSetter":true,"kind":"method","name":"query=","id":"query=1()","children":[{"ref":{"name":"String","refId":"dart.core/String"},"kind":"param","name":"value","id":"value"}],"line":"380"},{"isSetter":true,"kind":"method","name":"startedBefore=","id":"startedBefore=1()","children":[{"ref":{"name":"String","refId":"dart.core/String"},"kind":"param","name":"value","id":"value"}],"line":"383"},{"isSetter":true,"kind":"method","name":"startedAfter=","id":"startedAfter=1()","children":[{"ref":{"name":"String","refId":"dart.core/String"},"kind":"param","name":"value","id":"value"}],"line":"386"},{"isSetter":true,"kind":"method","name":"endedBefore=","id":"endedBefore=1()","children":[{"ref":{"name":"String","refId":"dart.core/String"},"kind":"param","name":"value","id":"value"}],"line":"389"},{"isSetter":true,"kind":"method","name":"endedAfter=","id":"endedAfter=1()","children":[{"ref":{"name":"String","refId":"dart.core/String"},"kind":"param","name":"value","id":"value"}],"line":"392"},{"isSetter":true,"kind":"method","name":"totalBytesGreater=","id":"totalBytesGreater=1()","children":[{"ref":{"name":"int","refId":"dart.core/int"},"kind":"param","name":"value","id":"value"}],"line":"395"},{"isSetter":true,"kind":"method","name":"totalBytesLess=","id":"totalBytesLess=1()","children":[{"ref":{"name":"int","refId":"dart.core/int"},"kind":"param","name":"value","id":"value"}],"line":"398"},{"isSetter":true,"kind":"method","name":"filenameRegex=","id":"filenameRegex=1()","children":[{"ref":{"name":"String","refId":"dart.core/String"},"kind":"param","name":"value","id":"value"}],"line":"401"},{"isSetter":true,"kind":"method","name":"urlRegex=","id":"urlRegex=1()","children":[{"ref":{"name":"String","refId":"dart.core/String"},"kind":"param","name":"value","id":"value"}],"line":"404"},{"isSetter":true,"kind":"method","name":"limit=","id":"limit=1()","children":[{"ref":{"name":"int","refId":"dart.core/int"},"kind":"param","name":"value","id":"value"}],"line":"407"},{"isSetter":true,"kind":"method","name":"orderBy=","id":"orderBy=1()","children":[{"ref":{"name":"String","refId":"dart.core/String"},"kind":"param","name":"value","id":"value"}],"line":"410"},{"isSetter":true,"kind":"method","name":"id=","id":"id=1()","children":[{"ref":{"name":"int","refId":"dart.core/int"},"kind":"param","name":"value","id":"value"}],"line":"413"},{"isSetter":true,"kind":"method","name":"url=","id":"url=1()","children":[{"ref":{"name":"String","refId":"dart.core/String"},"kind":"param","name":"value","id":"value"}],"line":"416"},{"isSetter":true,"kind":"method","name":"filename=","id":"filename=1()","children":[{"ref":{"name":"String","refId":"dart.core/String"},"kind":"param","name":"value","id":"value"}],"line":"419"},{"isSetter":true,"kind":"method","name":"danger=","id":"danger=1()","children":[{"ref":{"name":"DangerType","refId":"chrome.downloads/DangerType"},"kind":"param","name":"value","id":"value"}],"line":"422"},{"isSetter":true,"kind":"method","name":"mime=","id":"mime=1()","children":[{"ref":{"name":"String","refId":"dart.core/String"},"kind":"param","name":"value","id":"value"}],"line":"425"},{"isSetter":true,"kind":"method","name":"startTime=","id":"startTime=1()","children":[{"ref":{"name":"String","refId":"dart.core/String"},"kind":"param","name":"value","id":"value"}],"line":"428"},{"isSetter":true,"kind":"method","name":"endTime=","id":"endTime=1()","children":[{"ref":{"name":"String","refId":"dart.core/String"},"kind":"param","name":"value","id":"value"}],"line":"431"},{"isSetter":true,"kind":"method","name":"state=","id":"state=1()","children":[{"ref":{"name":"State","refId":"chrome.downloads/State"},"kind":"param","name":"value","id":"value"}],"line":"434"},{"isSetter":true,"kind":"method","name":"paused=","id":"paused=1()","children":[{"ref":{"name":"bool","refId":"dart.core/bool"},"kind":"param","name":"value","id":"value"}],"line":"437"},{"isSetter":true,"kind":"method","name":"error=","id":"error=1()","children":[{"ref":{"name":"InterruptReason","refId":"chrome.downloads/InterruptReason"},"kind":"param","name":"value","id":"value"}],"line":"440"},{"isSetter":true,"kind":"method","name":"bytesReceived=","id":"bytesReceived=1()","children":[{"ref":{"name":"int","refId":"dart.core/int"},"kind":"param","name":"value","id":"value"}],"line":"443"},{"isSetter":true,"kind":"method","name":"totalBytes=","id":"totalBytes=1()","children":[{"ref":{"name":"int","refId":"dart.core/int"},"kind":"param","name":"value","id":"value"}],"line":"446"},{"isSetter":true,"kind":"method","name":"fileSize=","id":"fileSize=1()","children":[{"ref":{"name":"int","refId":"dart.core/int"},"kind":"param","name":"value","id":"value"}],"line":"449"},{"isSetter":true,"kind":"method","name":"exists=","id":"exists=1()","children":[{"ref":{"name":"bool","refId":"dart.core/bool"},"kind":"param","name":"value","id":"value"}],"line":"452"},{"ref":{"name":"String","refId":"dart.core/String"},"kind":"property","name":"query","id":"query","line":"379"},{"ref":{"name":"String","refId":"dart.core/String"},"kind":"property","name":"startedBefore","id":"startedBefore","line":"382"},{"ref":{"name":"String","refId":"dart.core/String"},"kind":"property","name":"startedAfter","id":"startedAfter","line":"385"},{"ref":{"name":"String","refId":"dart.core/String"},"kind":"property","name":"endedBefore","id":"endedBefore","line":"388"},{"ref":{"name":"String","refId":"dart.core/String"},"kind":"property","name":"endedAfter","id":"endedAfter","line":"391"},{"ref":{"name":"int","refId":"dart.core/int"},"kind":"property","name":"totalBytesGreater","id":"totalBytesGreater","line":"394"},{"ref":{"name":"int","refId":"dart.core/int"},"kind":"property","name":"totalBytesLess","id":"totalBytesLess","line":"397"},{"ref":{"name":"String","refId":"dart.core/String"},"kind":"property","name":"filenameRegex","id":"filenameRegex","line":"400"},{"ref":{"name":"String","refId":"dart.core/String"},"kind":"property","name":"urlRegex","id":"urlRegex","line":"403"},{"ref":{"name":"int","refId":"dart.core/int"},"kind":"property","name":"limit","id":"limit","line":"406"},{"ref":{"name":"String","refId":"dart.core/String"},"kind":"property","name":"orderBy","id":"orderBy","line":"409"},{"ref":{"name":"int","refId":"dart.core/int"},"kind":"property","name":"id","id":"id","line":"412"},{"ref":{"name":"String","refId":"dart.core/String"},"kind":"property","name":"url","id":"url","line":"415"},{"ref":{"name":"String","refId":"dart.core/String"},"kind":"property","name":"filename","id":"filename","line":"418"},{"ref":{"name":"DangerType","refId":"chrome.downloads/DangerType"},"kind":"property","name":"danger","id":"danger","line":"421"},{"ref":{"name":"String","refId":"dart.core/String"},"kind":"property","name":"mime","id":"mime","line":"424"},{"ref":{"name":"String","refId":"dart.core/String"},"kind":"property","name":"startTime","id":"startTime","line":"427"},{"ref":{"name":"String","refId":"dart.core/String"},"kind":"property","name":"endTime","id":"endTime","line":"430"},{"ref":{"name":"State","refId":"chrome.downloads/State"},"kind":"property","name":"state","id":"state","line":"433"},{"ref":{"name":"bool","refId":"dart.core/bool"},"kind":"property","name":"paused","id":"paused","line":"436"},{"ref":{"name":"InterruptReason","refId":"chrome.downloads/InterruptReason"},"kind":"property","name":"error","id":"error","line":"439"},{"ref":{"name":"int","refId":"dart.core/int"},"kind":"property","name":"bytesReceived","id":"bytesReceived","line":"442"},{"ref":{"name":"int","refId":"dart.core/int"},"kind":"property","name":"totalBytes","id":"totalBytes","line":"445"},{"ref":{"name":"int","refId":"dart.core/int"},"kind":"property","name":"fileSize","id":"fileSize","line":"448"},{"ref":{"name":"bool","refId":"dart.core/bool"},"kind":"property","name":"exists","id":"exists","line":"451"},{"kind":"constructor","name":"","id":"25()","children":[{"ref":{"name":"String","refId":"dart.core/String"},"isOptional":true,"isNamed":true,"kind":"param","name":"query","id":"query"},{"ref":{"name":"String","refId":"dart.core/String"},"isOptional":true,"isNamed":true,"kind":"param","name":"startedBefore","id":"startedBefore"},{"ref":{"name":"String","refId":"dart.core/String"},"isOptional":true,"isNamed":true,"kind":"param","name":"startedAfter","id":"startedAfter"},{"ref":{"name":"String","refId":"dart.core/String"},"isOptional":true,"isNamed":true,"kind":"param","name":"endedBefore","id":"endedBefore"},{"ref":{"name":"String","refId":"dart.core/String"},"isOptional":true,"isNamed":true,"kind":"param","name":"endedAfter","id":"endedAfter"},{"ref":{"name":"int","refId":"dart.core/int"},"isOptional":true,"isNamed":true,"kind":"param","name":"totalBytesGreater","id":"totalBytesGreater"},{"ref":{"name":"int","refId":"dart.core/int"},"isOptional":true,"isNamed":true,"kind":"param","name":"totalBytesLess","id":"totalBytesLess"},{"ref":{"name":"String","refId":"dart.core/String"},"isOptional":true,"isNamed":true,"kind":"param","name":"filenameRegex","id":"filenameRegex"},{"ref":{"name":"String","refId":"dart.core/String"},"isOptional":true,"isNamed":true,"kind":"param","name":"urlRegex","id":"urlRegex"},{"ref":{"name":"int","refId":"dart.core/int"},"isOptional":true,"isNamed":true,"kind":"param","name":"limit","id":"limit"},{"ref":{"name":"String","refId":"dart.core/String"},"isOptional":true,"isNamed":true,"kind":"param","name":"orderBy","id":"orderBy"},{"ref":{"name":"int","refId":"dart.core/int"},"isOptional":true,"isNamed":true,"kind":"param","name":"id","id":"id"},{"ref":{"name":"String","refId":"dart.core/String"},"isOptional":true,"isNamed":true,"kind":"param","name":"url","id":"url"},{"ref":{"name":"String","refId":"dart.core/String"},"isOptional":true,"isNamed":true,"kind":"param","name":"filename","id":"filename"},{"ref":{"name":"DangerType","refId":"chrome.downloads/DangerType"},"isOptional":true,"isNamed":true,"kind":"param","name":"danger","id":"danger"},{"ref":{"name":"String","refId":"dart.core/String"},"isOptional":true,"isNamed":true,"kind":"param","name":"mime","id":"mime"},{"ref":{"name":"String","refId":"dart.core/String"},"isOptional":true,"isNamed":true,"kind":"param","name":"startTime","id":"startTime"},{"ref":{"name":"String","refId":"dart.core/String"},"isOptional":true,"isNamed":true,"kind":"param","name":"endTime","id":"endTime"},{"ref":{"name":"State","refId":"chrome.downloads/State"},"isOptional":true,"isNamed":true,"kind":"param","name":"state","id":"state"},{"ref":{"name":"bool","refId":"dart.core/bool"},"isOptional":true,"isNamed":true,"kind":"param","name":"paused","id":"paused"},{"ref":{"name":"InterruptReason","refId":"chrome.downloads/InterruptReason"},"isOptional":true,"isNamed":true,"kind":"param","name":"error","id":"error"},{"ref":{"name":"int","refId":"dart.core/int"},"isOptional":true,"isNamed":true,"kind":"param","name":"bytesReceived","id":"bytesReceived"},{"ref":{"name":"int","refId":"dart.core/int"},"isOptional":true,"isNamed":true,"kind":"param","name":"totalBytes","id":"totalBytes"},{"ref":{"name":"int","refId":"dart.core/int"},"isOptional":true,"isNamed":true,"kind":"param","name":"fileSize","id":"fileSize"},{"ref":{"name":"bool","refId":"dart.core/bool"},"isOptional":true,"isNamed":true,"kind":"param","name":"exists","id":"exists"}],"line":"349"},{"kind":"constructor","name":"fromProxy","id":"fromProxy1()","children":[{"ref":{"name":"JsObject","refId":"dart.js/JsObject"},"kind":"param","name":"proxy","id":"proxy"}],"line":"377"}],"line":"347"},{"superclass":{"name":"ChromeObject","refId":"chrome.src.common_exp/ChromeObject"},"kind":"class","name":"DownloadItem","id":"DownloadItem","children":[{"isSetter":true,"kind":"method","name":"id=","id":"id=1()","children":[{"ref":{"name":"int","refId":"dart.core/int"},"kind":"param","name":"value","id":"value"}],"line":"287"},{"isSetter":true,"kind":"method","name":"url=","id":"url=1()","children":[{"ref":{"name":"String","refId":"dart.core/String"},"kind":"param","name":"value","id":"value"}],"line":"290"},{"isSetter":true,"kind":"method","name":"referrer=","id":"referrer=1()","children":[{"ref":{"name":"String","refId":"dart.core/String"},"kind":"param","name":"value","id":"value"}],"line":"293"},{"isSetter":true,"kind":"method","name":"filename=","id":"filename=1()","children":[{"ref":{"name":"String","refId":"dart.core/String"},"kind":"param","name":"value","id":"value"}],"line":"296"},{"isSetter":true,"kind":"method","name":"incognito=","id":"incognito=1()","children":[{"ref":{"name":"bool","refId":"dart.core/bool"},"kind":"param","name":"value","id":"value"}],"line":"299"},{"isSetter":true,"kind":"method","name":"danger=","id":"danger=1()","children":[{"ref":{"name":"DangerType","refId":"chrome.downloads/DangerType"},"kind":"param","name":"value","id":"value"}],"line":"302"},{"isSetter":true,"kind":"method","name":"mime=","id":"mime=1()","children":[{"ref":{"name":"String","refId":"dart.core/String"},"kind":"param","name":"value","id":"value"}],"line":"305"},{"isSetter":true,"kind":"method","name":"startTime=","id":"startTime=1()","children":[{"ref":{"name":"String","refId":"dart.core/String"},"kind":"param","name":"value","id":"value"}],"line":"308"},{"isSetter":true,"kind":"method","name":"endTime=","id":"endTime=1()","children":[{"ref":{"name":"String","refId":"dart.core/String"},"kind":"param","name":"value","id":"value"}],"line":"311"},{"isSetter":true,"kind":"method","name":"estimatedEndTime=","id":"estimatedEndTime=1()","children":[{"ref":{"name":"String","refId":"dart.core/String"},"kind":"param","name":"value","id":"value"}],"line":"314"},{"isSetter":true,"kind":"method","name":"state=","id":"state=1()","children":[{"ref":{"name":"State","refId":"chrome.downloads/State"},"kind":"param","name":"value","id":"value"}],"line":"317"},{"isSetter":true,"kind":"method","name":"paused=","id":"paused=1()","children":[{"ref":{"name":"bool","refId":"dart.core/bool"},"kind":"param","name":"value","id":"value"}],"line":"320"},{"isSetter":true,"kind":"method","name":"canResume=","id":"canResume=1()","children":[{"ref":{"name":"bool","refId":"dart.core/bool"},"kind":"param","name":"value","id":"value"}],"line":"323"},{"isSetter":true,"kind":"method","name":"error=","id":"error=1()","children":[{"ref":{"name":"InterruptReason","refId":"chrome.downloads/InterruptReason"},"kind":"param","name":"value","id":"value"}],"line":"326"},{"isSetter":true,"kind":"method","name":"bytesReceived=","id":"bytesReceived=1()","children":[{"ref":{"name":"int","refId":"dart.core/int"},"kind":"param","name":"value","id":"value"}],"line":"329"},{"isSetter":true,"kind":"method","name":"totalBytes=","id":"totalBytes=1()","children":[{"ref":{"name":"int","refId":"dart.core/int"},"kind":"param","name":"value","id":"value"}],"line":"332"},{"isSetter":true,"kind":"method","name":"fileSize=","id":"fileSize=1()","children":[{"ref":{"name":"int","refId":"dart.core/int"},"kind":"param","name":"value","id":"value"}],"line":"335"},{"isSetter":true,"kind":"method","name":"exists=","id":"exists=1()","children":[{"ref":{"name":"bool","refId":"dart.core/bool"},"kind":"param","name":"value","id":"value"}],"line":"338"},{"isSetter":true,"kind":"method","name":"byExtensionId=","id":"byExtensionId=1()","children":[{"ref":{"name":"String","refId":"dart.core/String"},"kind":"param","name":"value","id":"value"}],"line":"341"},{"isSetter":true,"kind":"method","name":"byExtensionName=","id":"byExtensionName=1()","children":[{"ref":{"name":"String","refId":"dart.core/String"},"kind":"param","name":"value","id":"value"}],"line":"344"},{"ref":{"name":"int","refId":"dart.core/int"},"kind":"property","name":"id","id":"id","line":"286"},{"ref":{"name":"String","refId":"dart.core/String"},"kind":"property","name":"url","id":"url","line":"289"},{"ref":{"name":"String","refId":"dart.core/String"},"kind":"property","name":"referrer","id":"referrer","line":"292"},{"ref":{"name":"String","refId":"dart.core/String"},"kind":"property","name":"filename","id":"filename","line":"295"},{"ref":{"name":"bool","refId":"dart.core/bool"},"kind":"property","name":"incognito","id":"incognito","line":"298"},{"ref":{"name":"DangerType","refId":"chrome.downloads/DangerType"},"kind":"property","name":"danger","id":"danger","line":"301"},{"ref":{"name":"String","refId":"dart.core/String"},"kind":"property","name":"mime","id":"mime","line":"304"},{"ref":{"name":"String","refId":"dart.core/String"},"kind":"property","name":"startTime","id":"startTime","line":"307"},{"ref":{"name":"String","refId":"dart.core/String"},"kind":"property","name":"endTime","id":"endTime","line":"310"},{"ref":{"name":"String","refId":"dart.core/String"},"kind":"property","name":"estimatedEndTime","id":"estimatedEndTime","line":"313"},{"ref":{"name":"State","refId":"chrome.downloads/State"},"kind":"property","name":"state","id":"state","line":"316"},{"ref":{"name":"bool","refId":"dart.core/bool"},"kind":"property","name":"paused","id":"paused","line":"319"},{"ref":{"name":"bool","refId":"dart.core/bool"},"kind":"property","name":"canResume","id":"canResume","line":"322"},{"ref":{"name":"InterruptReason","refId":"chrome.downloads/InterruptReason"},"kind":"property","name":"error","id":"error","line":"325"},{"ref":{"name":"int","refId":"dart.core/int"},"kind":"property","name":"bytesReceived","id":"bytesReceived","line":"328"},{"ref":{"name":"int","refId":"dart.core/int"},"kind":"property","name":"totalBytes","id":"totalBytes","line":"331"},{"ref":{"name":"int","refId":"dart.core/int"},"kind":"property","name":"fileSize","id":"fileSize","line":"334"},{"ref":{"name":"bool","refId":"dart.core/bool"},"kind":"property","name":"exists","id":"exists","line":"337"},{"ref":{"name":"String","refId":"dart.core/String"},"kind":"property","name":"byExtensionId","id":"byExtensionId","line":"340"},{"ref":{"name":"String","refId":"dart.core/String"},"kind":"property","name":"byExtensionName","id":"byExtensionName","line":"343"},{"kind":"constructor","name":"","id":"20()","children":[{"ref":{"name":"int","refId":"dart.core/int"},"isOptional":true,"isNamed":true,"kind":"param","name":"id","id":"id"},{"ref":{"name":"String","refId":"dart.core/String"},"isOptional":true,"isNamed":true,"kind":"param","name":"url","id":"url"},{"ref":{"name":"String","refId":"dart.core/String"},"isOptional":true,"isNamed":true,"kind":"param","name":"referrer","id":"referrer"},{"ref":{"name":"String","refId":"dart.core/String"},"isOptional":true,"isNamed":true,"kind":"param","name":"filename","id":"filename"},{"ref":{"name":"bool","refId":"dart.core/bool"},"isOptional":true,"isNamed":true,"kind":"param","name":"incognito","id":"incognito"},{"ref":{"name":"DangerType","refId":"chrome.downloads/DangerType"},"isOptional":true,"isNamed":true,"kind":"param","name":"danger","id":"danger"},{"ref":{"name":"String","refId":"dart.core/String"},"isOptional":true,"isNamed":true,"kind":"param","name":"mime","id":"mime"},{"ref":{"name":"String","refId":"dart.core/String"},"isOptional":true,"isNamed":true,"kind":"param","name":"startTime","id":"startTime"},{"ref":{"name":"String","refId":"dart.core/String"},"isOptional":true,"isNamed":true,"kind":"param","name":"endTime","id":"endTime"},{"ref":{"name":"String","refId":"dart.core/String"},"isOptional":true,"isNamed":true,"kind":"param","name":"estimatedEndTime","id":"estimatedEndTime"},{"ref":{"name":"State","refId":"chrome.downloads/State"},"isOptional":true,"isNamed":true,"kind":"param","name":"state","id":"state"},{"ref":{"name":"bool","refId":"dart.core/bool"},"isOptional":true,"isNamed":true,"kind":"param","name":"paused","id":"paused"},{"ref":{"name":"bool","refId":"dart.core/bool"},"isOptional":true,"isNamed":true,"kind":"param","name":"canResume","id":"canResume"},{"ref":{"name":"InterruptReason","refId":"chrome.downloads/InterruptReason"},"isOptional":true,"isNamed":true,"kind":"param","name":"error","id":"error"},{"ref":{"name":"int","refId":"dart.core/int"},"isOptional":true,"isNamed":true,"kind":"param","name":"bytesReceived","id":"bytesReceived"},{"ref":{"name":"int","refId":"dart.core/int"},"isOptional":true,"isNamed":true,"kind":"param","name":"totalBytes","id":"totalBytes"},{"ref":{"name":"int","refId":"dart.core/int"},"isOptional":true,"isNamed":true,"kind":"param","name":"fileSize","id":"fileSize"},{"ref":{"name":"bool","refId":"dart.core/bool"},"isOptional":true,"isNamed":true,"kind":"param","name":"exists","id":"exists"},{"ref":{"name":"String","refId":"dart.core/String"},"isOptional":true,"isNamed":true,"kind":"param","name":"byExtensionId","id":"byExtensionId"},{"ref":{"name":"String","refId":"dart.core/String"},"isOptional":true,"isNamed":true,"kind":"param","name":"byExtensionName","id":"byExtensionName"}],"line":"261"},{"kind":"constructor","name":"fromProxy","id":"fromProxy1()","children":[{"ref":{"name":"JsObject","refId":"dart.js/JsObject"},"kind":"param","name":"proxy","id":"proxy"}],"line":"284"}],"line":"259"},{"superclass":{"name":"ChromeObject","refId":"chrome.src.common_exp/ChromeObject"},"kind":"class","name":"DownloadOptions","id":"DownloadOptions","children":[{"isSetter":true,"kind":"method","name":"url=","id":"url=1()","children":[{"ref":{"name":"String","refId":"dart.core/String"},"kind":"param","name":"value","id":"value"}],"line":"238"},{"isSetter":true,"kind":"method","name":"filename=","id":"filename=1()","children":[{"ref":{"name":"String","refId":"dart.core/String"},"kind":"param","name":"value","id":"value"}],"line":"241"},{"isSetter":true,"kind":"method","name":"conflictAction=","id":"conflictAction=1()","children":[{"ref":{"name":"FilenameConflictAction","refId":"chrome.downloads/FilenameConflictAction"},"kind":"param","name":"value","id":"value"}],"line":"244"},{"isSetter":true,"kind":"method","name":"saveAs=","id":"saveAs=1()","children":[{"ref":{"name":"bool","refId":"dart.core/bool"},"kind":"param","name":"value","id":"value"}],"line":"247"},{"isSetter":true,"kind":"method","name":"method=","id":"method=1()","children":[{"ref":{"name":"HttpMethod","refId":"chrome.downloads/HttpMethod"},"kind":"param","name":"value","id":"value"}],"line":"250"},{"isSetter":true,"kind":"method","name":"headers=","id":"headers=1()","children":[{"ref":{"name":"HeaderNameValuePair","refId":"chrome.downloads/HeaderNameValuePair"},"kind":"param","name":"value","id":"value"}],"line":"253"},{"isSetter":true,"kind":"method","name":"body=","id":"body=1()","children":[{"ref":{"name":"String","refId":"dart.core/String"},"kind":"param","name":"value","id":"value"}],"line":"256"},{"ref":{"name":"String","refId":"dart.core/String"},"kind":"property","name":"url","id":"url","line":"237"},{"ref":{"name":"String","refId":"dart.core/String"},"kind":"property","name":"filename","id":"filename","line":"240"},{"ref":{"name":"FilenameConflictAction","refId":"chrome.downloads/FilenameConflictAction"},"kind":"property","name":"conflictAction","id":"conflictAction","line":"243"},{"ref":{"name":"bool","refId":"dart.core/bool"},"kind":"property","name":"saveAs","id":"saveAs","line":"246"},{"ref":{"name":"HttpMethod","refId":"chrome.downloads/HttpMethod"},"kind":"property","name":"method","id":"method","line":"249"},{"ref":{"name":"HeaderNameValuePair","refId":"chrome.downloads/HeaderNameValuePair"},"kind":"property","name":"headers","id":"headers","line":"252"},{"ref":{"name":"String","refId":"dart.core/String"},"kind":"property","name":"body","id":"body","line":"255"},{"kind":"constructor","name":"","id":"7()","children":[{"ref":{"name":"String","refId":"dart.core/String"},"isOptional":true,"isNamed":true,"kind":"param","name":"url","id":"url"},{"ref":{"name":"String","refId":"dart.core/String"},"isOptional":true,"isNamed":true,"kind":"param","name":"filename","id":"filename"},{"ref":{"name":"FilenameConflictAction","refId":"chrome.downloads/FilenameConflictAction"},"isOptional":true,"isNamed":true,"kind":"param","name":"conflictAction","id":"conflictAction"},{"ref":{"name":"bool","refId":"dart.core/bool"},"isOptional":true,"isNamed":true,"kind":"param","name":"saveAs","id":"saveAs"},{"ref":{"name":"HttpMethod","refId":"chrome.downloads/HttpMethod"},"isOptional":true,"isNamed":true,"kind":"param","name":"method","id":"method"},{"ref":{"name":"HeaderNameValuePair","refId":"chrome.downloads/HeaderNameValuePair"},"isOptional":true,"isNamed":true,"kind":"param","name":"headers","id":"headers"},{"ref":{"name":"String","refId":"dart.core/String"},"isOptional":true,"isNamed":true,"kind":"param","name":"body","id":"body"}],"line":"225"},{"kind":"constructor","name":"fromProxy","id":"fromProxy1()","children":[{"ref":{"name":"JsObject","refId":"dart.js/JsObject"},"kind":"param","name":"proxy","id":"proxy"}],"line":"235"}],"line":"223"},{"superclass":{"name":"ChromeObject","refId":"chrome.src.common_exp/ChromeObject"},"kind":"class","name":"FilenameSuggestion","id":"FilenameSuggestion","children":[{"isSetter":true,"kind":"method","name":"filename=","id":"filename=1()","children":[{"ref":{"name":"String","refId":"dart.core/String"},"kind":"param","name":"value","id":"value"}],"line":"217"},{"isSetter":true,"kind":"method","name":"conflictAction=","id":"conflictAction=1()","children":[{"ref":{"name":"FilenameConflictAction","refId":"chrome.downloads/FilenameConflictAction"},"kind":"param","name":"value","id":"value"}],"line":"220"},{"ref":{"name":"String","refId":"dart.core/String"},"kind":"property","name":"filename","id":"filename","line":"216"},{"ref":{"name":"FilenameConflictAction","refId":"chrome.downloads/FilenameConflictAction"},"kind":"property","name":"conflictAction","id":"conflictAction","line":"219"},{"kind":"constructor","name":"","id":"2()","children":[{"ref":{"name":"String","refId":"dart.core/String"},"isOptional":true,"isNamed":true,"kind":"param","name":"filename","id":"filename"},{"ref":{"name":"FilenameConflictAction","refId":"chrome.downloads/FilenameConflictAction"},"isOptional":true,"isNamed":true,"kind":"param","name":"conflictAction","id":"conflictAction"}],"line":"209"},{"kind":"constructor","name":"fromProxy","id":"fromProxy1()","children":[{"ref":{"name":"JsObject","refId":"dart.js/JsObject"},"kind":"param","name":"proxy","id":"proxy"}],"line":"214"}],"line":"207"},{"superclass":{"name":"ChromeObject","refId":"chrome.src.common_exp/ChromeObject"},"kind":"class","name":"HeaderNameValuePair","id":"HeaderNameValuePair","children":[{"isSetter":true,"kind":"method","name":"name=","id":"name=1()","children":[{"ref":{"name":"String","refId":"dart.core/String"},"kind":"param","name":"value","id":"value"}],"line":"201"},{"isSetter":true,"kind":"method","name":"value=","id":"value=1()","children":[{"ref":{"name":"String","refId":"dart.core/String"},"kind":"param","name":"value","id":"value"}],"line":"204"},{"ref":{"name":"String","refId":"dart.core/String"},"kind":"property","name":"name","id":"name","line":"200"},{"ref":{"name":"String","refId":"dart.core/String"},"kind":"property","name":"value","id":"value","line":"203"},{"kind":"constructor","name":"","id":"2()","children":[{"ref":{"name":"String","refId":"dart.core/String"},"isOptional":true,"isNamed":true,"kind":"param","name":"name","id":"name"},{"ref":{"name":"String","refId":"dart.core/String"},"isOptional":true,"isNamed":true,"kind":"param","name":"value","id":"value"}],"line":"193"},{"kind":"constructor","name":"fromProxy","id":"fromProxy1()","children":[{"ref":{"name":"JsObject","refId":"dart.js/JsObject"},"kind":"param","name":"proxy","id":"proxy"}],"line":"198"}],"line":"191"},{"superclass":{"name":"ChromeEnum","refId":"chrome.src.common_exp/ChromeEnum"},"kind":"class","name":"State","id":"State","children":[{"ref":{"name":"State","refId":"chrome.downloads/State"},"isStatic":true,"kind":"variable","name":"IN_PROGRESS","id":"IN_PROGRESS","line":"182"},{"ref":{"name":"State","refId":"chrome.downloads/State"},"isStatic":true,"kind":"variable","name":"INTERRUPTED","id":"INTERRUPTED","line":"183"},{"ref":{"name":"State","refId":"chrome.downloads/State"},"isStatic":true,"kind":"variable","name":"COMPLETE","id":"COMPLETE","line":"184"},{"ref":{"name":"List","refId":"dart.core/List","arguments":[{"name":"State","refId":"chrome.downloads/State"}]},"isStatic":true,"kind":"variable","name":"VALUES","id":"VALUES","line":"186"},{"kind":"constructor","name":"_","id":"_1()","children":[{"ref":{"name":"String","refId":"dart.core/String"},"kind":"param","name":"str","id":"str"}],"isPrivate":true,"line":"188"}],"line":"181"},{"superclass":{"name":"ChromeEnum","refId":"chrome.src.common_exp/ChromeEnum"},"kind":"class","name":"DangerType","id":"DangerType","children":[{"ref":{"name":"DangerType","refId":"chrome.downloads/DangerType"},"isStatic":true,"kind":"variable","name":"FILE","id":"FILE","line":"167"},{"ref":{"name":"DangerType","refId":"chrome.downloads/DangerType"},"isStatic":true,"kind":"variable","name":"URL","id":"URL","line":"168"},{"ref":{"name":"DangerType","refId":"chrome.downloads/DangerType"},"isStatic":true,"kind":"variable","name":"CONTENT","id":"CONTENT","line":"169"},{"ref":{"name":"DangerType","refId":"chrome.downloads/DangerType"},"isStatic":true,"kind":"variable","name":"UNCOMMON","id":"UNCOMMON","line":"170"},{"ref":{"name":"DangerType","refId":"chrome.downloads/DangerType"},"isStatic":true,"kind":"variable","name":"HOST","id":"HOST","line":"171"},{"ref":{"name":"DangerType","refId":"chrome.downloads/DangerType"},"isStatic":true,"kind":"variable","name":"UNWANTED","id":"UNWANTED","line":"172"},{"ref":{"name":"DangerType","refId":"chrome.downloads/DangerType"},"isStatic":true,"kind":"variable","name":"SAFE","id":"SAFE","line":"173"},{"ref":{"name":"DangerType","refId":"chrome.downloads/DangerType"},"isStatic":true,"kind":"variable","name":"ACCEPTED","id":"ACCEPTED","line":"174"},{"ref":{"name":"List","refId":"dart.core/List","arguments":[{"name":"DangerType","refId":"chrome.downloads/DangerType"}]},"isStatic":true,"kind":"variable","name":"VALUES","id":"VALUES","line":"176"},{"kind":"constructor","name":"_","id":"_1()","children":[{"ref":{"name":"String","refId":"dart.core/String"},"kind":"param","name":"str","id":"str"}],"isPrivate":true,"line":"178"}],"line":"166"},{"superclass":{"name":"ChromeEnum","refId":"chrome.src.common_exp/ChromeEnum"},"kind":"class","name":"InterruptReason","id":"InterruptReason","children":[{"ref":{"name":"InterruptReason","refId":"chrome.downloads/InterruptReason"},"isStatic":true,"kind":"variable","name":"FILE_FAILED","id":"FILE_FAILED","line":"139"},{"ref":{"name":"InterruptReason","refId":"chrome.downloads/InterruptReason"},"isStatic":true,"kind":"variable","name":"FILE_ACCESS_DENIED","id":"FILE_ACCESS_DENIED","line":"140"},{"ref":{"name":"InterruptReason","refId":"chrome.downloads/InterruptReason"},"isStatic":true,"kind":"variable","name":"FILE_NO_SPACE","id":"FILE_NO_SPACE","line":"141"},{"ref":{"name":"InterruptReason","refId":"chrome.downloads/InterruptReason"},"isStatic":true,"kind":"variable","name":"FILE_NAME_TOO_LONG","id":"FILE_NAME_TOO_LONG","line":"142"},{"ref":{"name":"InterruptReason","refId":"chrome.downloads/InterruptReason"},"isStatic":true,"kind":"variable","name":"FILE_TOO_LARGE","id":"FILE_TOO_LARGE","line":"143"},{"ref":{"name":"InterruptReason","refId":"chrome.downloads/InterruptReason"},"isStatic":true,"kind":"variable","name":"FILE_VIRUS_INFECTED","id":"FILE_VIRUS_INFECTED","line":"144"},{"ref":{"name":"InterruptReason","refId":"chrome.downloads/InterruptReason"},"isStatic":true,"kind":"variable","name":"FILE_TRANSIENT_ERROR","id":"FILE_TRANSIENT_ERROR","line":"145"},{"ref":{"name":"InterruptReason","refId":"chrome.downloads/InterruptReason"},"isStatic":true,"kind":"variable","name":"FILE_BLOCKED","id":"FILE_BLOCKED","line":"146"},{"ref":{"name":"InterruptReason","refId":"chrome.downloads/InterruptReason"},"isStatic":true,"kind":"variable","name":"FILE_SECURITY_CHECK_FAILED","id":"FILE_SECURITY_CHECK_FAILED","line":"147"},{"ref":{"name":"InterruptReason","refId":"chrome.downloads/InterruptReason"},"isStatic":true,"kind":"variable","name":"FILE_TOO_SHORT","id":"FILE_TOO_SHORT","line":"148"},{"ref":{"name":"InterruptReason","refId":"chrome.downloads/InterruptReason"},"isStatic":true,"kind":"variable","name":"NETWORK_FAILED","id":"NETWORK_FAILED","line":"149"},{"ref":{"name":"InterruptReason","refId":"chrome.downloads/InterruptReason"},"isStatic":true,"kind":"variable","name":"NETWORK_TIMEOUT","id":"NETWORK_TIMEOUT","line":"150"},{"ref":{"name":"InterruptReason","refId":"chrome.downloads/InterruptReason"},"isStatic":true,"kind":"variable","name":"NETWORK_DISCONNECTED","id":"NETWORK_DISCONNECTED","line":"151"},{"ref":{"name":"InterruptReason","refId":"chrome.downloads/InterruptReason"},"isStatic":true,"kind":"variable","name":"NETWORK_SERVER_DOWN","id":"NETWORK_SERVER_DOWN","line":"152"},{"ref":{"name":"InterruptReason","refId":"chrome.downloads/InterruptReason"},"isStatic":true,"kind":"variable","name":"SERVER_FAILED","id":"SERVER_FAILED","line":"153"},{"ref":{"name":"InterruptReason","refId":"chrome.downloads/InterruptReason"},"isStatic":true,"kind":"variable","name":"SERVER_NO_RANGE","id":"SERVER_NO_RANGE","line":"154"},{"ref":{"name":"InterruptReason","refId":"chrome.downloads/InterruptReason"},"isStatic":true,"kind":"variable","name":"SERVER_PRECONDITION","id":"SERVER_PRECONDITION","line":"155"},{"ref":{"name":"InterruptReason","refId":"chrome.downloads/InterruptReason"},"isStatic":true,"kind":"variable","name":"SERVER_BAD_CONTENT","id":"SERVER_BAD_CONTENT","line":"156"},{"ref":{"name":"InterruptReason","refId":"chrome.downloads/InterruptReason"},"isStatic":true,"kind":"variable","name":"USER_CANCELED","id":"USER_CANCELED","line":"157"},{"ref":{"name":"InterruptReason","refId":"chrome.downloads/InterruptReason"},"isStatic":true,"kind":"variable","name":"USER_SHUTDOWN","id":"USER_SHUTDOWN","line":"158"},{"ref":{"name":"InterruptReason","refId":"chrome.downloads/InterruptReason"},"isStatic":true,"kind":"variable","name":"CRASH","id":"CRASH","line":"159"},{"ref":{"name":"List","refId":"dart.core/List","arguments":[{"name":"InterruptReason","refId":"chrome.downloads/InterruptReason"}]},"isStatic":true,"kind":"variable","name":"VALUES","id":"VALUES","line":"161"},{"kind":"constructor","name":"_","id":"_1()","children":[{"ref":{"name":"String","refId":"dart.core/String"},"kind":"param","name":"str","id":"str"}],"isPrivate":true,"line":"163"}],"line":"138"},{"superclass":{"name":"ChromeEnum","refId":"chrome.src.common_exp/ChromeEnum"},"kind":"class","name":"HttpMethod","id":"HttpMethod","children":[{"ref":{"name":"HttpMethod","refId":"chrome.downloads/HttpMethod"},"isStatic":true,"kind":"variable","name":"GET","id":"GET","line":"130"},{"ref":{"name":"HttpMethod","refId":"chrome.downloads/HttpMethod"},"isStatic":true,"kind":"variable","name":"POST","id":"POST","line":"131"},{"ref":{"name":"List","refId":"dart.core/List","arguments":[{"name":"HttpMethod","refId":"chrome.downloads/HttpMethod"}]},"isStatic":true,"kind":"variable","name":"VALUES","id":"VALUES","line":"133"},{"kind":"constructor","name":"_","id":"_1()","children":[{"ref":{"name":"String","refId":"dart.core/String"},"kind":"param","name":"str","id":"str"}],"isPrivate":true,"line":"135"}],"line":"129"},{"superclass":{"name":"ChromeEnum","refId":"chrome.src.common_exp/ChromeEnum"},"kind":"class","name":"FilenameConflictAction","id":"FilenameConflictAction","children":[{"ref":{"name":"FilenameConflictAction","refId":"chrome.downloads/FilenameConflictAction"},"isStatic":true,"kind":"variable","name":"UNIQUIFY","id":"UNIQUIFY","line":"120"},{"ref":{"name":"FilenameConflictAction","refId":"chrome.downloads/FilenameConflictAction"},"isStatic":true,"kind":"variable","name":"OVERWRITE","id":"OVERWRITE","line":"121"},{"ref":{"name":"FilenameConflictAction","refId":"chrome.downloads/FilenameConflictAction"},"isStatic":true,"kind":"variable","name":"PROMPT","id":"PROMPT","line":"122"},{"ref":{"name":"List","refId":"dart.core/List","arguments":[{"name":"FilenameConflictAction","refId":"chrome.downloads/FilenameConflictAction"}]},"isStatic":true,"kind":"variable","name":"VALUES","id":"VALUES","line":"124"},{"kind":"constructor","name":"_","id":"_1()","children":[{"ref":{"name":"String","refId":"dart.core/String"},"kind":"param","name":"str","id":"str"}],"isPrivate":true,"line":"126"}],"line":"119"},{"superclass":{"name":"Object","refId":"dart.core/Object"},"kind":"class","name":"OnDeterminingFilenameEvent","id":"OnDeterminingFilenameEvent","children":[{"ref":{"name":"DownloadItem","refId":"chrome.downloads/DownloadItem"},"isFinal":true,"kind":"variable","name":"downloadItem","id":"downloadItem","line":"112"},{"ref":{"name":"SuggestFilenameCallback","refId":"chrome.src.common_exp/SuggestFilenameCallback"},"isFinal":true,"kind":"variable","name":"suggest","id":"suggest","line":"114"},{"kind":"constructor","name":"","id":"2()","children":[{"ref":{"name":"DownloadItem","refId":"chrome.downloads/DownloadItem"},"initializedField":{"name":"downloadItem","refId":"chrome.downloads/OnDeterminingFilenameEvent/downloadItem"},"kind":"param","name":"downloadItem","id":"downloadItem"},{"ref":{"name":"SuggestFilenameCallback","refId":"chrome.src.common_exp/SuggestFilenameCallback"},"initializedField":{"name":"suggest","refId":"chrome.downloads/OnDeterminingFilenameEvent/suggest"},"kind":"param","name":"suggest","id":"suggest"}],"line":"116"}],"line":"110"},{"superclass":{"name":"Object","refId":"dart.core/Object"},"kind":"class","name":"ChromeDownloads","id":"ChromeDownloads","children":[{"returnType":{"name":"Future","refId":"dart.async/Future","arguments":[{"name":"int","refId":"dart.core/int"}]},"kind":"method","name":"download","id":"download1()","children":[{"ref":{"name":"DownloadOptions","refId":"chrome.downloads/DownloadOptions"},"kind":"param","name":"options","id":"options"}],"line":"15"},{"returnType":{"name":"Future","refId":"dart.async/Future","arguments":[{"name":"DownloadItem","refId":"chrome.downloads/DownloadItem"}]},"kind":"method","name":"search","id":"search1()","children":[{"ref":{"name":"DownloadQuery","refId":"chrome.downloads/DownloadQuery"},"kind":"param","name":"query","id":"query"}],"line":"21"},{"returnType":{"name":"Future","refId":"dart.async/Future"},"kind":"method","name":"pause","id":"pause1()","children":[{"ref":{"name":"int","refId":"dart.core/int"},"kind":"param","name":"downloadId","id":"downloadId"}],"line":"27"},{"returnType":{"name":"Future","refId":"dart.async/Future"},"kind":"method","name":"resume","id":"resume1()","children":[{"ref":{"name":"int","refId":"dart.core/int"},"kind":"param","name":"downloadId","id":"downloadId"}],"line":"33"},{"returnType":{"name":"Future","refId":"dart.async/Future"},"kind":"method","name":"cancel","id":"cancel1()","children":[{"ref":{"name":"int","refId":"dart.core/int"},"kind":"param","name":"downloadId","id":"downloadId"}],"line":"39"},{"returnType":{"name":"Future","refId":"dart.async/Future","arguments":[{"name":"String","refId":"dart.core/String"}]},"kind":"method","name":"getFileIcon","id":"getFileIcon2()","children":[{"ref":{"name":"int","refId":"dart.core/int"},"kind":"param","name":"downloadId","id":"downloadId"},{"ref":{"name":"GetFileIconOptions","refId":"chrome.downloads/GetFileIconOptions"},"isOptional":true,"kind":"param","name":"options","id":"options"}],"line":"45"},{"returnType":{"name":"void","refId":"void"},"kind":"method","name":"open","id":"open1()","children":[{"ref":{"name":"int","refId":"dart.core/int"},"kind":"param","name":"downloadId","id":"downloadId"}],"line":"51"},{"returnType":{"name":"void","refId":"void"},"kind":"method","name":"show","id":"show1()","children":[{"ref":{"name":"int","refId":"dart.core/int"},"kind":"param","name":"downloadId","id":"downloadId"}],"line":"55"},{"returnType":{"name":"void","refId":"void"},"kind":"method","name":"showDefaultFolder","id":"showDefaultFolder0()","line":"59"},{"returnType":{"name":"Future","refId":"dart.async/Future","arguments":[{"name":"int","refId":"dart.core/int"}]},"kind":"method","name":"erase","id":"erase1()","children":[{"ref":{"name":"DownloadQuery","refId":"chrome.downloads/DownloadQuery"},"kind":"param","name":"query","id":"query"}],"line":"63"},{"returnType":{"name":"Future","refId":"dart.async/Future"},"kind":"method","name":"removeFile","id":"removeFile1()","children":[{"ref":{"name":"int","refId":"dart.core/int"},"kind":"param","name":"downloadId","id":"downloadId"}],"line":"69"},{"returnType":{"name":"Future","refId":"dart.async/Future"},"kind":"method","name":"acceptDanger","id":"acceptDanger1()","children":[{"ref":{"name":"int","refId":"dart.core/int"},"kind":"param","name":"downloadId","id":"downloadId"}],"line":"75"},{"returnType":{"name":"void","refId":"void"},"kind":"method","name":"drag","id":"drag1()","children":[{"ref":{"name":"int","refId":"dart.core/int"},"kind":"param","name":"downloadId","id":"downloadId"}],"line":"81"},{"returnType":{"name":"void","refId":"void"},"kind":"method","name":"setShelfEnabled","id":"setShelfEnabled1()","children":[{"ref":{"name":"bool","refId":"dart.core/bool"},"kind":"param","name":"enabled","id":"enabled"}],"line":"85"},{"ref":{"name":"Stream","refId":"dart.async/Stream","arguments":[{"name":"DownloadItem","refId":"chrome.downloads/DownloadItem"}]},"kind":"property","name":"onCreated","id":"onCreated","line":"89"},{"ref":{"name":"Stream","refId":"dart.async/Stream","arguments":[{"name":"int","refId":"dart.core/int"}]},"kind":"property","name":"onErased","id":"onErased","line":"94"},{"ref":{"name":"Stream","refId":"dart.async/Stream","arguments":[{"name":"DownloadDelta","refId":"chrome.downloads/DownloadDelta"}]},"kind":"property","name":"onChanged","id":"onChanged","line":"99"},{"ref":{"name":"Stream","refId":"dart.async/Stream","arguments":[{"name":"OnDeterminingFilenameEvent","refId":"chrome.downloads/OnDeterminingFilenameEvent"}]},"kind":"property","name":"onDeterminingFilename","id":"onDeterminingFilename","line":"104"},{"ref":{"name":"JsObject","refId":"dart.js/JsObject"},"isStatic":true,"isFinal":true,"kind":"variable","name":"_downloads","id":"_downloads","isPrivate":true,"line":"11"},{"ref":{"name":"ChromeStreamController","refId":"chrome.src.common/ChromeStreamController","arguments":[{"name":"DownloadItem","refId":"chrome.downloads/DownloadItem"}]},"isFinal":true,"kind":"variable","name":"_onCreated","id":"_onCreated","isPrivate":true,"line":"91"},{"ref":{"name":"ChromeStreamController","refId":"chrome.src.common/ChromeStreamController","arguments":[{"name":"int","refId":"dart.core/int"}]},"isFinal":true,"kind":"variable","name":"_onErased","id":"_onErased","isPrivate":true,"line":"96"},{"ref":{"name":"ChromeStreamController","refId":"chrome.src.common/ChromeStreamController","arguments":[{"name":"DownloadDelta","refId":"chrome.downloads/DownloadDelta"}]},"isFinal":true,"kind":"variable","name":"_onChanged","id":"_onChanged","isPrivate":true,"line":"101"},{"ref":{"name":"ChromeStreamController","refId":"chrome.src.common/ChromeStreamController","arguments":[{"name":"OnDeterminingFilenameEvent","refId":"chrome.downloads/OnDeterminingFilenameEvent"}]},"isFinal":true,"kind":"variable","name":"_onDeterminingFilename","id":"_onDeterminingFilename","isPrivate":true,"line":"106"},{"kind":"constructor","name":"_","id":"_0()","isPrivate":true,"line":"13"}],"line":"10"}],"uri":"file:///home/ubuntu/src/github.com/dart-gde/chrome_gen.dart/lib/gen/downloads.dart","line":"3"}